{
	"configurations" : 
	[
		{
			"directories" : 
			[
				{
					"build" : ".",
					"minimumCMakeVersion" : 
					{
						"string" : "3.0"
					},
					"projectIndex" : 0,
					"source" : ".",
					"targetIndexes" : 
					[
						0
					]
				}
			],
			"name" : "Debug",
			"projects" : 
			[
				{
					"directoryIndexes" : 
					[
						0
					],
					"name" : "SETR_TP2_CLIENT",
					"targetIndexes" : 
					[
						0
					]
				}
			],
			"targets" : 
			[
				{
					"directoryIndex" : 0,
					"id" : "tp2client::@6890427a1f51a3e7e1df",
					"jsonFile" : "target-tp2client-Debug-305dbf7c042483466467.json",
					"name" : "tp2client",
					"projectIndex" : 0
				}
			]
		}
	],
	"kind" : "codemodel",
	"paths" : 
	{
		"build" : "/home/mikael/projets/SETR/src/daemonFuse/build",
		"source" : "/home/mikael/projets/SETR/src/daemonFuse"
	},
	"version" : 
	{
		"major" : 2,
		"minor" : 2
	}
}
